dj_raincheck/__init__.py
dj_raincheck/apps.py
dj_raincheck/decorators.py
dj_raincheck/py.typed
dj_raincheck/signals.py
dj_raincheck/store.py
dj_raincheck-0.5.0.dist-info/WHEEL
dj_raincheck-0.5.0.dist-info/METADATA
dj_raincheck-0.5.0.dist-info/RECORD
