Metadata-Version: 2.3
Name: dj-raincheck
Version: 0.5.0
Summary: Simple asynchronous execution for Django
Keywords: django,web,request
Author: Aron Jones, Adam Hill
Author-email: Aron Jones <aron.jones@gmail.com>, Adam Hill <adam@adamghill.com>
License: The MIT License (MIT)
Classifier: Development Status :: 3 - Alpha
Classifier: Framework :: Django
Classifier: Framework :: Django :: 3.2
Classifier: Framework :: Django :: 4.0
Classifier: Framework :: Django :: 4.1
Classifier: Framework :: Django :: 4.2
Classifier: Intended Audience :: Developers
Classifier: License :: OSI Approved :: MIT License
Classifier: Programming Language :: Python :: 3.10
Classifier: Programming Language :: Python :: 3.11
Classifier: Topic :: Software Development :: Libraries :: Python Modules
Requires-Dist: django>=3.2
Requires-Python: >=3.10
Project-URL: homepage, https://github.com/adamghill/dj-raincheck/
Project-URL: repository, https://github.com/adamghill/dj-raincheck.git
